MANIFEST.in
README.md
setup.cfg
setup.py
versioneer.py
spawn/__init__.py
spawn/__main__.py
spawn/_version.py
spawn.egg-info/PKG-INFO
spawn.egg-info/SOURCES.txt
spawn.egg-info/dependency_links.txt
spawn.egg-info/entry_points.txt
spawn.egg-info/requires.txt
spawn.egg-info/top_level.txt
spawn/cli/__init__.py
spawn/cli/functions.py
spawn/config/__init__.py
spawn/config/base.py
spawn/config/command_line.py
spawn/config/composite.py
spawn/config/default.py
spawn/config/ini_file.py
spawn/errors/__init__.py
spawn/interface/__init__.py
spawn/interface/config.py
spawn/interface/local.py
spawn/interface/spawn.py
spawn/interface/util.py
spawn/parsers/__init__.py
spawn/parsers/constants.py
spawn/parsers/generators.py
spawn/parsers/macros.py
spawn/parsers/specification_parser.py
spawn/parsers/value_libraries.py
spawn/parsers/value_proxy.py
spawn/plugins/__init__.py
spawn/plugins/json_input_file.py
spawn/plugins/plugin_loader.py
spawn/runners/__init__.py
spawn/runners/process_runner.py
spawn/schedulers/__init__.py
spawn/schedulers/luigi.py
spawn/simulation_inputs/__init__.py
spawn/simulation_inputs/json.py
spawn/simulation_inputs/simulation_input.py
spawn/spawners/__init__.py
spawn/spawners/single_input_file.py
spawn/spawners/task_spawner.py
spawn/specification/__init__.py
spawn/specification/combinators.py
spawn/specification/converters.py
spawn/specification/evaluators.py
spawn/specification/generator_methods.py
spawn/specification/specification.py
spawn/specification/value_proxy.py
spawn/tasks/__init__.py
spawn/tasks/base.py
spawn/tasks/generate.py
spawn/tasks/simulation.py
spawn/tasks/task_list_parameter.py
spawn/util/__init__.py
spawn/util/hash.py
spawn/util/logging.py
spawn/util/path_builder.py
spawn/util/prettyspec.py
spawn/util/property.py
spawn/util/string.py
spawn/util/validation.py