Metadata-Version: 2.1
Name: spawn
Version: 0.2.0
Summary: Spawn is a python package that allows users to concisely specify and execute a large number of tasks with complex and co-dependent input parameter variations
Home-page: https://github.com/Simmovation/spawn
Author: Simmovation Ltd
Author-email: info@simmovation.tech
License: GPLv3
Platform: any
Requires-Python: >=3.6,<4
Provides-Extra: publish
Provides-Extra: docs
Provides-Extra: test
